{"skeleton":{"hash":"C2Vk3kFotlLfG7kmBu7Z5TRAgIQ","spine":"3.6.53","width":129.28,"height":120.32,"images":"./img/"},"bones":[{"name":"Socre_Pomi_Wild"},{"name":"zong","parent":"Socre_Pomi_Wild","scaleY":1.02},{"name":"BG","parent":"zong"},{"name":"BG2","parent":"zong"},{"name":"BG3","parent":"zong","scaleX":-1},{"name":"BG4","parent":"zong","scaleX":-1},{"name":"Wild","parent":"zong","y":-1.38},{"name":"D","parent":"Wild","x":44.99,"y":-5.97,"scaleX":2,"scaleY":2},{"name":"Dark","parent":"zong"},{"name":"Fire_lizi","parent":"zong","y":14.78,"scaleX":1.98,"scaleY":2},{"name":"I","parent":"Wild","x":-2.19,"y":-4.74,"scaleX":2,"scaleY":2},{"name":"L","parent":"Wild","x":19.05,"y":-4.74,"scaleX":2,"scaleY":2},{"name":"W","parent":"Wild","x":-38.34,"y":-4.74,"scaleX":2,"scaleY":2},{"name":"di","parent":"zong","scaleX":2,"scaleY":2},{"name":"jianzhu","parent":"zong","y":-1.3},{"name":"jianzhusg","parent":"jianzhu","y":-3.93,"scaleX":4,"scaleY":4}],"slots":[{"name":"cut","bone":"zong","attachment":"cut"},{"name":"wild3","bone":"di","attachment":"wild3"},{"name":"wild2","bone":"di","attachment":"wild2"},{"name":"wildb1","bone":"BG","attachment":"wildb1"},{"name":"wildb3","bone":"BG3"},{"name":"wildb2","bone":"BG2"},{"name":"lizi","bone":"Fire_lizi"},{"name":"wildb4","bone":"BG4"},{"name":"wild4","bone":"jianzhu","attachment":"wild4"},{"name":"wild2 (2)","bone":"Wild","attachment":"wild2 (2)"},{"name":"jianzhusg","bone":"jianzhusg","blend":"additive"},{"name":"wild2 (2)2","bone":"Wild","blend":"additive"},{"name":"wild_W_30","bone":"W","blend":"additive"},{"name":"wild_I","bone":"I","blend":"additive"},{"name":"wild_L","bone":"L","blend":"additive"},{"name":"wild_D","bone":"D","blend":"additive"},{"name":"4in1_Pomi_wild00_1","bone":"Dark"}],"skins":{"default":{"4in1_Pomi_wild00_1":{"4in1_Pomi_wild00_1":{"width":130,"height":120}},"cut":{"cut":{"type":"clipping","end":"wild4","vertexCount":4,"vertices":[-64.02,58,64.06,58.01,64.03,-58.05,-64.04,-58.01],"color":"3a3acdff"}},"jianzhusg":{"Pomi_jianzhusg_01":{"width":32,"height":27},"Pomi_jianzhusg_02":{"width":32,"height":27},"Pomi_jianzhusg_03":{"width":32,"height":27},"Pomi_jianzhusg_04":{"width":32,"height":27},"Pomi_jianzhusg_05":{"width":32,"height":27},"Pomi_jianzhusg_06":{"width":32,"height":27},"Pomi_jianzhusg_07":{"width":32,"height":27},"Pomi_jianzhusg_08":{"width":32,"height":27},"Pomi_jianzhusg_09":{"width":32,"height":27}},"lizi":{"Pomi_wild_lizi_01":{"width":65,"height":45},"Pomi_wild_lizi_02":{"width":65,"height":45},"Pomi_wild_lizi_03":{"width":65,"height":45},"Pomi_wild_lizi_04":{"width":65,"height":45},"Pomi_wild_lizi_05":{"width":65,"height":45},"Pomi_wild_lizi_06":{"width":65,"height":45},"Pomi_wild_lizi_07":{"width":65,"height":45}},"wild2":{"wild2":{"width":64,"height":58}},"wild2 (2)":{"wild2 (2)":{"width":128,"height":116}},"wild2 (2)2":{"wild2 (2)":{"width":128,"height":116}},"wild3":{"wild3":{"scaleX":1.01,"scaleY":1.01,"width":64,"height":58}},"wild4":{"wild4":{"width":128,"height":116}},"wild_D":{"wild_d_30":{"width":20,"height":28}},"wild_I":{"wild_i_30":{"width":12,"height":27}},"wild_L":{"wild_l_30":{"width":19,"height":28}},"wild_W_30":{"wild_W_30":{"width":27,"height":28}},"wildb1":{"wildb1":{"width":128,"height":116}},"wildb2":{"wildb1":{"width":128,"height":116}},"wildb3":{"wildb1":{"width":128,"height":116}},"wildb4":{"wildb1":{"width":128,"height":116}}}},"animations":{"Dark":{"slots":{"4in1_Pomi_wild00_1":{"attachment":[{"time":0,"name":"4in1_Pomi_wild00_1"}]},"jianzhusg":{"attachment":[{"time":0,"name":null}]},"lizi":{"attachment":[{"time":0,"name":null}]},"wild2":{"attachment":[{"time":0,"name":null}]},"wild3":{"attachment":[{"time":0,"name":null}]},"wild4":{"attachment":[{"time":0,"name":null}]},"wild2 (2)":{"attachment":[{"time":0,"name":null}]},"wild2 (2)2":{"attachment":[{"time":0,"name":null}]},"wild_D":{"attachment":[{"time":0,"name":null}]},"wild_I":{"attachment":[{"time":0,"name":null}]},"wild_L":{"attachment":[{"time":0,"name":null}]},"wild_W_30":{"attachment":[{"time":0,"name":null}]},"wildb1":{"attachment":[{"time":0,"name":null}]},"wildb2":{"attachment":[{"time":0,"name":null}]},"wildb3":{"attachment":[{"time":0,"name":null}]},"wildb4":{"attachment":[{"time":0,"name":null}]}}},"actionframe":{"slots":{"4in1_Pomi_wild00_1":{"attachment":[{"time":0,"name":null}]},"jianzhusg":{"attachment":[{"time":0,"name":null},{"time":1.3333,"name":null},{"time":1.3667,"name":"Pomi_jianzhusg_01"},{"time":1.4667,"name":"Pomi_jianzhusg_02"},{"time":1.5667,"name":"Pomi_jianzhusg_03"},{"time":1.6667,"name":"Pomi_jianzhusg_04"},{"time":1.7667,"name":"Pomi_jianzhusg_05"},{"time":1.8667,"name":"Pomi_jianzhusg_06"},{"time":1.9667,"name":"Pomi_jianzhusg_07"},{"time":2.0667,"name":"Pomi_jianzhusg_08"},{"time":2.1667,"name":"Pomi_jianzhusg_09"}]},"lizi":{"color":[{"time":0,"color":"ffffff00"},{"time":0.4,"color":"ffffffff","curve":"stepped"},{"time":2,"color":"ffffffff"},{"time":2.4,"color":"ffffff00"}],"attachment":[{"time":0,"name":"Pomi_wild_lizi_01"},{"time":0.1,"name":"Pomi_wild_lizi_02"},{"time":0.2,"name":"Pomi_wild_lizi_03"},{"time":0.3,"name":"Pomi_wild_lizi_04"},{"time":0.4,"name":"Pomi_wild_lizi_05"},{"time":0.5,"name":"Pomi_wild_lizi_06"},{"time":0.6,"name":"Pomi_wild_lizi_07"},{"time":0.6667,"name":"Pomi_wild_lizi_01"},{"time":0.7667,"name":"Pomi_wild_lizi_02"},{"time":0.8667,"name":"Pomi_wild_lizi_03"},{"time":0.9667,"name":"Pomi_wild_lizi_04"},{"time":1.0667,"name":"Pomi_wild_lizi_05"},{"time":1.1667,"name":"Pomi_wild_lizi_06"},{"time":1.2667,"name":"Pomi_wild_lizi_07"},{"time":1.3667,"name":"Pomi_wild_lizi_01"},{"time":1.4667,"name":"Pomi_wild_lizi_02"},{"time":1.5667,"name":"Pomi_wild_lizi_03"},{"time":1.6667,"name":"Pomi_wild_lizi_04"},{"time":1.7667,"name":"Pomi_wild_lizi_05"},{"time":1.8667,"name":"Pomi_wild_lizi_06"},{"time":1.9667,"name":"Pomi_wild_lizi_01"},{"time":2.0667,"name":"Pomi_wild_lizi_02"},{"time":2.1667,"name":"Pomi_wild_lizi_03"},{"time":2.2667,"name":"Pomi_wild_lizi_04"},{"time":2.3667,"name":"Pomi_wild_lizi_05"}]},"wild4":{"attachment":[{"time":0,"name":"wild4"}]},"wild2 (2)":{"attachment":[{"time":0,"name":"wild2 (2)"}]},"wild2 (2)2":{"color":[{"time":0,"color":"ffffff00","curve":"stepped"},{"time":0.4333,"color":"ffffff00"},{"time":0.5333,"color":"ffffffff","curve":"stepped"},{"time":0.8,"color":"ffffffff"},{"time":1.1333,"color":"ffffff00"}],"attachment":[{"time":0,"name":"wild2 (2)"}]},"wild_D":{"color":[{"time":1.7667,"color":"ffffff00"},{"time":1.9667,"color":"ffffffff"},{"time":2.3667,"color":"ffffff00"}],"attachment":[{"time":1.7333,"name":null},{"time":1.7667,"name":"wild_d_30"}]},"wild_I":{"color":[{"time":1.5333,"color":"ffffff00"},{"time":1.7333,"color":"ffffffff"},{"time":2.1333,"color":"ffffff00"}],"attachment":[{"time":1.5,"name":null},{"time":1.5333,"name":"wild_i_30"}]},"wild_L":{"color":[{"time":1.6333,"color":"ffffff00"},{"time":1.8333,"color":"ffffffff"},{"time":2.2667,"color":"ffffff00"}],"attachment":[{"time":1.6,"name":null},{"time":1.6333,"name":"wild_l_30"}]},"wild_W_30":{"color":[{"time":1.4,"color":"ffffff00"},{"time":1.6,"color":"ffffffff"},{"time":2,"color":"ffffff00"}],"attachment":[{"time":1.3667,"name":null},{"time":1.4,"name":"wild_W_30"}]},"wildb1":{"color":[{"time":1.8,"color":"ffffffff"},{"time":2.4,"color":"ffffff00"}],"attachment":[{"time":0,"name":"wildb1"}]},"wildb2":{"color":[{"time":0,"color":"ffffff00","curve":"stepped"},{"time":1.8,"color":"ffffff00"},{"time":2.4,"color":"ffffffff"}],"attachment":[{"time":0,"name":null},{"time":1.7667,"name":null},{"time":1.8,"name":"wildb1"}]},"wildb3":{"color":[{"time":1.8,"color":"ffffffff"},{"time":2.4,"color":"ffffff00"}],"attachment":[{"time":0,"name":null}]},"wildb4":{"color":[{"time":0,"color":"ffffff00","curve":"stepped"},{"time":1.8,"color":"ffffff00"},{"time":2.4,"color":"ffffffff"}],"attachment":[{"time":0,"name":null},{"time":1.7667,"name":null},{"time":1.8,"name":"wildb1"}]}},"bones":{"Wild":{"scale":[{"time":0,"x":1,"y":1,"curve":[0.324,0.17,0.746,0.95]},{"time":0.2333,"x":0.95,"y":0.95,"curve":[0.25,0,0.75,1]},{"time":0.5333,"x":1.17,"y":1.17},{"time":0.8,"x":1.2,"y":1.2,"curve":[0.25,0,0.75,1]},{"time":1.1,"x":0.9,"y":0.9,"curve":[0.25,0,0.75,1]},{"time":1.2667,"x":1,"y":1}]},"BG":{"translate":[{"time":0,"x":0,"y":0},{"time":2.4,"x":15.69,"y":30.84}]},"BG2":{"translate":[{"time":1.8,"x":-10.04,"y":-14.29},{"time":2.4,"x":0,"y":0}]},"BG3":{"translate":[{"time":0,"x":0,"y":0},{"time":2.4,"x":15.69,"y":30.84}]},"BG4":{"translate":[{"time":1.8,"x":-12.61,"y":-12.58},{"time":2.4,"x":0,"y":0}]}}},"idleframe":{"slots":{"4in1_Pomi_wild00_1":{"attachment":[{"time":0,"name":null}]},"jianzhusg":{"attachment":[{"time":0,"name":null}]},"lizi":{"attachment":[{"time":0,"name":null}]},"wild4":{"attachment":[{"time":0,"name":"wild4"}]},"wild2 (2)":{"attachment":[{"time":0,"name":"wild2 (2)"}]},"wild2 (2)2":{"attachment":[{"time":0,"name":null}]},"wild_D":{"attachment":[{"time":0,"name":null}]},"wild_I":{"attachment":[{"time":0,"name":null}]},"wild_L":{"attachment":[{"time":0,"name":null}]},"wild_W_30":{"attachment":[{"time":0,"name":null}]},"wildb1":{"attachment":[{"time":0,"name":"wildb1"}]},"wildb2":{"attachment":[{"time":0,"name":null}]},"wildb3":{"attachment":[{"time":0,"name":null}]},"wildb4":{"attachment":[{"time":0,"name":null}]}}}}}